numbers_extract.py
Numbers_Extract-1.0.6.dist-info/LICENSE
Numbers_Extract-1.0.6.dist-info/METADATA
Numbers_Extract-1.0.6.dist-info/WHEEL
Numbers_Extract-1.0.6.dist-info/top_level.txt
Numbers_Extract-1.0.6.dist-info/RECORD
