Metadata-Version: 2.1
Name: Numbers-Extract
Version: 1.0.6
Summary: Numbers extract from string
Home-page: UNKNOWN
Author: Fayas Noushad
License: MIT
Project-URL: Tracker, https://github.com/FayasNoushad/Numbers-Extract/issues
Project-URL: Source, https://github.com/FayasNoushad/Numbers-Extract
Platform: UNKNOWN
Classifier: Intended Audience :: Developers
Classifier: Natural Language :: English
Classifier: Programming Language :: Python
Classifier: License :: OSI Approved :: MIT License
Classifier: Operating System :: OS Independent
Requires-Python: >=3.6
License-File: LICENSE
Requires-Dist: check-number
